simple_type_check/__init__.py
simple_type_check/callable_info.py
simple_type_check/py.typed
simple_type_check/top_level_check.py
simple_type_check/type_check.py
simple_type_check/default/__init__.py
simple_type_check/default/basic.py
simple_type_check/default/complex.py
simple_type_checker-2.2.0.dist-info/LICENSE
simple_type_checker-2.2.0.dist-info/METADATA
simple_type_checker-2.2.0.dist-info/WHEEL
simple_type_checker-2.2.0.dist-info/top_level.txt
simple_type_checker-2.2.0.dist-info/RECORD
