Metadata-Version: 2.1
Name: simple_type_checker
Version: 2.2.0
Summary: A small extendable python type checker library
License: GPL
Project-URL: Homepage, https://github.com/zwimer/simple_type_checker
Classifier: Programming Language :: Python :: 3
Classifier: Programming Language :: Python :: 3.10
Requires-Python: >=3.10
License-File: LICENSE
